{
    "/js/app.js": "/js/app.js",
    "/js/compiled/registrar.js?h=c565b7c56429d617": "/js/compiled/registrar.js?h=c565b7c56429d617",
    "/js/compiled/users.js?h=59234265bd176504": "/js/compiled/users.js?h=59234265bd176504",
    "/js/compiled/usersedit.js?h=aa437d997fb47bb8": "/js/compiled/usersedit.js?h=aa437d997fb47bb8",
    "/js/compiled/changepass.js?h=522c100756e7564d": "/js/compiled/changepass.js?h=522c100756e7564d",
    "/js/compiled/roles.js?h=59bac55dc2344908": "/js/compiled/roles.js?h=59bac55dc2344908",
    "/js/compiled/rolesregist.js?h=becccbd7c05ff4db": "/js/compiled/rolesregist.js?h=becccbd7c05ff4db",
    "/js/compiled/rolesedit.js?h=07437401cfe61102": "/js/compiled/rolesedit.js?h=07437401cfe61102",
    "/js/compiled/indexprogra.js?h=228fc13eff810baf": "/js/compiled/indexprogra.js?h=228fc13eff810baf",
    "/js/compiled/programar.js?h=33da1651489597b7": "/js/compiled/programar.js?h=33da1651489597b7",
    "/js/compiled/programaedit.js?h=029fd3dd3f2060f5": "/js/compiled/programaedit.js?h=029fd3dd3f2060f5",
    "/js/compiled/indexproflota.js?h=76d2031c202154c2": "/js/compiled/indexproflota.js?h=76d2031c202154c2",
    "/js/compiled/progfloasig.js?h=9ea51aaf96dcbdd2": "/js/compiled/progfloasig.js?h=9ea51aaf96dcbdd2",
    "/js/compiled/indexproflotarep.js?h=083ef6256b2df65a": "/js/compiled/indexproflotarep.js?h=083ef6256b2df65a",
    "/js/compiled/reporteproflota.js?h=ece1c4e940b4aa8a": "/js/compiled/reporteproflota.js?h=ece1c4e940b4aa8a",
    "/js/compiled/indexinsti.js?h=9050dd27ab7d2fe5": "/js/compiled/indexinsti.js?h=9050dd27ab7d2fe5",
    "/js/compiled/institucion.js?h=b5810e503a2a0ea8": "/js/compiled/institucion.js?h=b5810e503a2a0ea8",
    "/js/compiled/instiedit.js?h=be1789ab1c4b2580": "/js/compiled/instiedit.js?h=be1789ab1c4b2580",
    "/js/compiled/indexasiginsti.js?h=ffe3a230a40c5346": "/js/compiled/indexasiginsti.js?h=ffe3a230a40c5346",
    "/js/compiled/asiginsti.js?h=aab1bb6d9f6baf05": "/js/compiled/asiginsti.js?h=aab1bb6d9f6baf05",
    "/js/compiled/indexdespacho.js?h=b6d79a683b3aec95": "/js/compiled/indexdespacho.js?h=b6d79a683b3aec95",
    "/js/compiled/despasig.js?h=1c7a4e4929180716": "/js/compiled/despasig.js?h=1c7a4e4929180716",
    "/css/app.css": "/css/app.css",
    "/js/compiled/indexproflotarep.js?h=3da5a248df3bcdcb": "/js/compiled/indexproflotarep.js?h=3da5a248df3bcdcb",
    "/js/compiled/indexproflotarep.js?h=107b388ad3c9d8f9": "/js/compiled/indexproflotarep.js?h=107b388ad3c9d8f9",
    "/js/compiled/indexproflotarep.js?h=6fa3faf231d34d11": "/js/compiled/indexproflotarep.js?h=6fa3faf231d34d11",
    "/js/compiled/indexproflotarep.js?h=b85275bb40967072": "/js/compiled/indexproflotarep.js?h=b85275bb40967072",
    "/js/compiled/indexproflotarep.js?h=a0b5d6f3dd1f45c8": "/js/compiled/indexproflotarep.js?h=a0b5d6f3dd1f45c8",
    "/js/compiled/indexproflotarep.js?h=1a02898472c9d0da": "/js/compiled/indexproflotarep.js?h=1a02898472c9d0da",
    "/js/compiled/indexproflotarep.js?h=3493675358b24905": "/js/compiled/indexproflotarep.js?h=3493675358b24905",
    "/js/compiled/indexproflotarep.js?h=2b740d85041d430b": "/js/compiled/indexproflotarep.js?h=2b740d85041d430b",
    "/js/compiled/indexproflotarep.js?h=b40ab2abff4b83f7": "/js/compiled/indexproflotarep.js?h=b40ab2abff4b83f7",
    "/js/compiled/indexproflotarep.js?h=fa52192841c52a6d": "/js/compiled/indexproflotarep.js?h=fa52192841c52a6d",
    "/js/compiled/indexproflotarep.js?h=a34d15b684110fdc": "/js/compiled/indexproflotarep.js?h=a34d15b684110fdc",
    "/js/compiled/indexproflotarep.js?h=f000e30e2c2f63f5": "/js/compiled/indexproflotarep.js?h=f000e30e2c2f63f5",
    "/js/compiled/indexproflotarep.js?h=79a1204027665e3d": "/js/compiled/indexproflotarep.js?h=79a1204027665e3d",
    "/js/compiled/indexproflotarep.js?h=1108933271c5d2cf": "/js/compiled/indexproflotarep.js?h=1108933271c5d2cf"
}
